examples/__init__.py
examples/concertbot/__init__.py
examples/concertbot/actions.py
examples/concertbot/train.py
examples/concertbot/train_interactive.py
examples/concertbot/visualize.py
examples/nlg_server/__init__.py
examples/nlg_server/nlg_server.py
examples/restaurantbot/__init__.py
examples/restaurantbot/actions.py
examples/restaurantbot/bot.py
examples/restaurantbot/policy.py
rasa_core/__init__.py
rasa_core/agent.py
rasa_core/broker.py
rasa_core/config.py
rasa_core/constants.py
rasa_core/conversation.py
rasa_core/default_config.yml
rasa_core/dispatcher.py
rasa_core/domain.py
rasa_core/evaluate.py
rasa_core/exceptions.py
rasa_core/featurizers.py
rasa_core/interpreter.py
rasa_core/processor.py
rasa_core/remote.py
rasa_core/restore.py
rasa_core/run.py
rasa_core/server.py
rasa_core/slots.py
rasa_core/test.py
rasa_core/tracker_store.py
rasa_core/trackers.py
rasa_core/train.py
rasa_core/utils.py
rasa_core/version.py
rasa_core/visualize.py
rasa_core/actions/__init__.py
rasa_core/actions/action.py
rasa_core/channels/__init__.py
rasa_core/channels/botframework.py
rasa_core/channels/callback.py
rasa_core/channels/channel.py
rasa_core/channels/console.py
rasa_core/channels/facebook.py
rasa_core/channels/mattermost.py
rasa_core/channels/rasa_chat.py
rasa_core/channels/rocketchat.py
rasa_core/channels/slack.py
rasa_core/channels/socketio.py
rasa_core/channels/telegram.py
rasa_core/channels/twilio.py
rasa_core/channels/webexteams.py
rasa_core/cli/__init__.py
rasa_core/cli/arguments.py
rasa_core/cli/run.py
rasa_core/cli/test.py
rasa_core/cli/train.py
rasa_core/cli/visualization.py
rasa_core/events/__init__.py
rasa_core/nlg/__init__.py
rasa_core/nlg/callback.py
rasa_core/nlg/generator.py
rasa_core/nlg/template.py
rasa_core/policies/__init__.py
rasa_core/policies/embedding_policy.py
rasa_core/policies/ensemble.py
rasa_core/policies/fallback.py
rasa_core/policies/form_policy.py
rasa_core/policies/keras_policy.py
rasa_core/policies/mapping_policy.py
rasa_core-0.14.5.dist-info/LICENSE.txt
rasa_core-0.14.5.dist-info/METADATA
rasa_core-0.14.5.dist-info/WHEEL
rasa_core-0.14.5.dist-info/top_level.txt
rasa_core-0.14.5.dist-info/RECORD
