Metadata-Version: 2.1
Name: rasa-core
Version: 0.14.5
Summary: Machine learning based dialogue engine for conversational software.
Home-page: https://rasa.com
Author: Rasa Technologies GmbH
Author-email: hi@rasa.com
Maintainer: Tom Bocklisch
Maintainer-email: tom@rasa.com
License: Apache 2.0
Download-URL: https://github.com/RasaHQ/rasa_core/archive/0.14.5.tar.gz
Project-URL: Bug Reports, https://github.com/rasahq/rasa_core/issues
Project-URL: Source, https://github.com/rasahq/rasa_core
Keywords: nlp machine-learning machine-learning-library bot bots botkit rasa conversational-agents conversational-ai chatbotchatbot-framework bot-framework
Platform: UNKNOWN
Classifier: Development Status :: 4 - Beta
Classifier: Intended Audience :: Developers
Classifier: License :: OSI Approved :: Apache Software License
Classifier: Programming Language :: Python
Classifier: Programming Language :: Python :: 3.5
Classifier: Programming Language :: Python :: 3.6
Classifier: Programming Language :: Python :: 3.7
Classifier: Topic :: Software Development :: Libraries
Requires-Dist: jsonpickle (~=1.0)
Requires-Dist: redis (~=2.0)
Requires-Dist: fakeredis (~=0.10.0)
Requires-Dist: pymongo (~=3.7)
Requires-Dist: numpy (~=1.16)
Requires-Dist: scipy (~=1.2)
Requires-Dist: typing (~=3.0)
Requires-Dist: requests (~=2.20)
Requires-Dist: tensorflow (~=1.13.0)
Requires-Dist: apscheduler (~=3.0)
Requires-Dist: tqdm (~=4.0)
Requires-Dist: networkx (~=2.2)
Requires-Dist: fbmessenger (~=5.0)
Requires-Dist: pykwalify (~=1.7.0)
Requires-Dist: coloredlogs (~=10.0)
Requires-Dist: ruamel.yaml (~=0.15.0)
Requires-Dist: flask (~=1.0)
Requires-Dist: flask-cors (~=3.0)
Requires-Dist: scikit-learn (~=0.20.0)
Requires-Dist: slackclient (~=1.0)
Requires-Dist: python-telegram-bot (~=11.0)
Requires-Dist: twilio (~=6.0)
Requires-Dist: webexteamssdk (~=1.0)
Requires-Dist: mattermostwrapper (~=2.0)
Requires-Dist: rocketchat-API (~=0.6.0)
Requires-Dist: colorhash (~=1.0)
Requires-Dist: pika (~=0.12.0)
Requires-Dist: jsonschema (~=2.6)
Requires-Dist: packaging (~=18.0)
Requires-Dist: gevent (~=1.3)
Requires-Dist: pytz (~=2018.9)
Requires-Dist: python-dateutil (~=2.7)
Requires-Dist: rasa-nlu (~=0.15)
Requires-Dist: rasa-core-sdk (~=0.14)
Requires-Dist: colorclass (~=2.2)
Requires-Dist: terminaltables (~=3.1)
Requires-Dist: questionary (>=1.0.1)
Requires-Dist: flask-jwt-simple (~=0.0.3)
Requires-Dist: python-socketio (~=3.0)
Requires-Dist: pydot (~=1.4)
Provides-Extra: test
Requires-Dist: pytest (~=3.0) ; extra == 'test'
Requires-Dist: pytest-pycodestyle (~=1.3) ; extra == 'test'
Requires-Dist: pytest-cov (~=2.0) ; extra == 'test'
Requires-Dist: pytest-localserver (~=0.4.0) ; extra == 'test'
Requires-Dist: treq (~=17.0) ; extra == 'test'
Requires-Dist: freezegun (~=0.3.0) ; extra == 'test'
Requires-Dist: nbsphinx (>=0.3) ; extra == 'test'
Requires-Dist: matplotlib (~=2.2) ; extra == 'test'
Requires-Dist: responses (~=0.9.0) ; extra == 'test'
Requires-Dist: httpretty (~=0.9.0) ; extra == 'test'
